qpharos/__init__.py
qpharos/analyzer.py
qpharos/api.py
qpharos/models.py
qpharos/molecular_generation.py
qpharos/simple.py
qpharos/core/__init__.py
qpharos/core/config.py
qpharos/core/pipeline.py
qpharos/core/quantum_backend.py
qpharos/layers/__init__.py
qpharos/layers/layer1_encoding.py
qpharos/layers/layer2_binding.py
qpharos/layers/layer2_binding_dcqaoa.py
qpharos/layers/layer3_admet.py
qpharos/layers/layer4_generation.py
qpharos/layers/layer5_dynamics.py
qpharos/utils/__init__.py
qpharos-2.0.1.dist-info/licenses/LICENSE
qpharos-2.0.1.dist-info/METADATA
qpharos-2.0.1.dist-info/WHEEL
qpharos-2.0.1.dist-info/entry_points.txt
qpharos-2.0.1.dist-info/top_level.txt
qpharos-2.0.1.dist-info/RECORD
