Metadata-Version: 2.4
Name: qpharos
Version: 2.0.1
Summary: Quantum Drug Discovery with DC-QAOA Docking - 5-Layer Quantum Architecture powered by BioQL
Home-page: https://bioql.bio/qpharos
Author: SpectrixRD
Author-email: contact@bioql.bio
License: Apache-2.0
Project-URL: Documentation, https://docs.bioql.bio/qpharos
Project-URL: Source, https://github.com/spectrixrd/qpharos
Project-URL: Tracker, https://github.com/spectrixrd/qpharos/issues
Project-URL: Homepage, https://bioql.bio/qpharos
Project-URL: BioQL Platform, https://bioql.bio
Keywords: quantum computing drug discovery pharmaceutical docking vqe qaoa qec ibm-quantum
Classifier: Development Status :: 5 - Production/Stable
Classifier: Intended Audience :: Science/Research
Classifier: Intended Audience :: Healthcare Industry
Classifier: Topic :: Scientific/Engineering :: Chemistry
Classifier: Topic :: Scientific/Engineering :: Physics
Classifier: Topic :: Scientific/Engineering :: Bio-Informatics
Classifier: License :: OSI Approved :: Apache Software License
Classifier: Programming Language :: Python :: 3
Classifier: Programming Language :: Python :: 3.8
Classifier: Programming Language :: Python :: 3.9
Classifier: Programming Language :: Python :: 3.10
Classifier: Programming Language :: Python :: 3.11
Classifier: Programming Language :: Python :: 3.12
Classifier: Operating System :: OS Independent
Requires-Python: >=3.8
License-File: LICENSE
Requires-Dist: bioql>=6.0.1
Requires-Dist: quillow>=1.0.0
Requires-Dist: numpy>=1.21.0
Requires-Dist: pydantic>=2.0.0
Provides-Extra: dev
Requires-Dist: pytest>=7.0.0; extra == "dev"
Requires-Dist: pytest-cov>=4.0.0; extra == "dev"
Requires-Dist: black>=23.0.0; extra == "dev"
Requires-Dist: flake8>=6.0.0; extra == "dev"
Requires-Dist: mypy>=1.0.0; extra == "dev"
Provides-Extra: docs
Requires-Dist: sphinx>=5.0.0; extra == "docs"
Requires-Dist: sphinx-rtd-theme>=1.2.0; extra == "docs"
Dynamic: author
Dynamic: author-email
Dynamic: classifier
Dynamic: description
Dynamic: description-content-type
Dynamic: home-page
Dynamic: keywords
Dynamic: license
Dynamic: license-file
Dynamic: project-url
Dynamic: provides-extra
Dynamic: requires-dist
Dynamic: requires-python
Dynamic: summary
